Metadata-Version: 2.4
Name: semantic-layer-tool
Version: 0.1.0
Home-page: https://github.com/preset-io/backend-sdk
Author: Beto Dealmeida
Author-email: tmph2003 <tmph2003@gmail.com>
License: MIT License
Project-URL: Homepage, https://github.com/tmph2003/superset-sdk-python
Platform: any
Requires-Python: >=3.7
Requires-Dist: pandas>=1.0
Requires-Dist: requests
